{
  "date": "2025-10-20",
  "theme": "Wallonie",
  "facts": [
    "La Wallonie est l'une des trois régions de la Belgique, couvrant approximativement 55% du territoire du pays.",
    "La région wallonne est divisée en cinq provinces : le Hainaut, le Brabant wallon, Liège, Luxembourg et Namur.",
    "La Wallonie est connue pour son patrimoine industriel et minier, avec des sites tels que le Bois du Cazier, classé au patrimoine mondial de l'UNESCO."
  ],
  "anecdote": "Lors de la révolution belge de 1830, les Wallons ont joué un rôle clé dans la lutte pour l'indépendance de la Belgique vis-à-vis des Pays-Bas.",
  "quiz": {
    "question": "Quelle est la capitale de la Wallonie ?",
    "options": [
      "Bruxelles",
      "Namur",
      "Liège"
    ],
    "answer": "Namur"
  }
}